cmbot/__init__.py
cmbot/cache.cp313-win_amd64.pyd
cmbot/cache.pyi
cmbot/cmdline.cp313-win_amd64.pyd
cmbot/cmdline.pyi
cmbot/cmzip.cp313-win_amd64.pyd
cmbot/cmzip.pyi
cmbot/pdf.cp313-win_amd64.pyd
cmbot/pdf.pyi
cmbot/rpa_logging.cp313-win_amd64.pyd
cmbot/rpa_logging.pyi
cmbot/utils.cp313-win_amd64.pyd
cmbot/utils.pyi
cmbot/web.cp313-win_amd64.pyd
cmbot/web.pyi
cmbot/work_calendar.cp313-win_amd64.pyd
cmbot/work_calendar.pyi
cmbot/app/__init__.py
cmbot/app/date_select.cp313-win_amd64.pyd
cmbot/app/date_select.pyi
cmbot/app/dialog.cp313-win_amd64.pyd
cmbot/app/dialog.pyi
cmbot/commands/__init__.py
cmbot/commands/cache.cp313-win_amd64.pyd
cmbot/commands/cache.pyi
cmbot/commands/chrome.cp313-win_amd64.pyd
cmbot/commands/chrome.pyi
cmbot/commands/config.cp313-win_amd64.pyd
cmbot/commands/config.pyi
cmbot/commands/genprocess.cp313-win_amd64.pyd
cmbot/commands/genprocess.pyi
cmbot/commands/hello.cp313-win_amd64.pyd
cmbot/commands/hello.pyi
cmbot/commands/publish.cp313-win_amd64.pyd
cmbot/commands/publish.pyi
cmbot/commands/utils.cp313-win_amd64.pyd
cmbot/commands/utils.pyi
cmbot/templates/process_template.py.tpl
cmbot/win32/__init__.py
cmbot/win32/clipboard.cp313-win_amd64.pyd
cmbot/win32/clipboard.pyi
cmbot/win32/screenshot.cp313-win_amd64.pyd
cmbot/win32/screenshot.pyi
cmbot/win32/upload.cp313-win_amd64.pyd
cmbot/win32/upload.pyi
cmbot-0.0.7.dist-info/METADATA
cmbot-0.0.7.dist-info/WHEEL
cmbot-0.0.7.dist-info/entry_points.txt
cmbot-0.0.7.dist-info/top_level.txt
cmbot-0.0.7.dist-info/RECORD
